pyrsig/__init__.py
pyrsig/bin/__init__.py
pyrsig/cmaq/__init__.py
pyrsig/cmaq/pair.py
pyrsig/data/DescribeCoverage.csv
pyrsig/data/__init__.py
pyrsig/data/pyrsigrc.json
pyrsig/emiss/__init__.py
pyrsig/emiss/_emg.py
pyrsig/emiss/_flux.py
pyrsig/grids/__init__.py
pyrsig/tests/__init__.py
pyrsig/tests/test_api.py
pyrsig/tests/test_bin.py
pyrsig/tests/test_coards.py
pyrsig/tests/test_dataframes.py
pyrsig/tests/test_gui.py
pyrsig/tests/test_ioapi.py
pyrsig/tests/test_misc.py
pyrsig/tests/test_xdr.py
pyrsig/utils/__init__.py
pyrsig/xdr/__init__.py
pyrsig-0.11.1.dist-info/licenses/LICENSE
pyrsig-0.11.1.dist-info/METADATA
pyrsig-0.11.1.dist-info/WHEEL
pyrsig-0.11.1.dist-info/top_level.txt
pyrsig-0.11.1.dist-info/RECORD
