Metadata-Version: 2.4
Name: pyrsig
Version: 0.11.1
Summary: Python interface to RSIG Web API
Home-page: https://github.com/barronh/pyrsig
Author: Barron H. Henderson
Author-email: barronh@gmail.com
Classifier: Programming Language :: Python :: 3
Classifier: License :: OSI Approved :: GNU General Public License v3 (GPLv3)
Classifier: Development Status :: 4 - Beta
Classifier: Operating System :: OS Independent
Requires-Python: >=3.6
License-File: LICENSE
Requires-Dist: pandas
Requires-Dist: xarray
Requires-Dist: requests
Provides-Extra: polygon
Requires-Dist: geopandas; extra == "polygon"
Provides-Extra: emiss
Requires-Dist: scipy; extra == "emiss"
Dynamic: author
Dynamic: author-email
Dynamic: classifier
Dynamic: description
Dynamic: description-content-type
Dynamic: home-page
Dynamic: license-file
Dynamic: provides-extra
Dynamic: requires-dist
Dynamic: requires-python
Dynamic: summary
